{
  "source_run": "TEST_RUN_0001",
  "source_path": "project\\runs\\TEST_RUN_0001\\artifacts",
  "promoted_utc": "2025-09-13T11:48:55Z",
  "git_commit": "0b2f4ee92d90f1681b824d8e89895fa01d214e23",
  "files": [
    {
      "name": "feature_columns.json",
      "sha256_16": "4f53cda18c2baa0c"
    },
    {
      "name": "feature_provenance.json",
      "sha256_16": "44136fa355b3678a"
    },
    {
      "name": "features_full.parquet",
      "sha256_16": "ef1979a65d8c0674"
    },
    {
      "name": "metrics.json",
      "sha256_16": "56e42b210bf50b75"
    },
    {
      "name": "model_readmission.joblib",
      "sha256_16": "a665a45920422f9d"
    },
    {
      "name": "preprocessor.joblib",
      "sha256_16": "b3a8e0e1f9ab1bfe"
    },
    {
      "name": "threshold.txt",
      "sha256_16": "44896b09365746b5"
    }
  ],
  "included_extras": [],
  "backup_dir": null,
  "dry_run": false
}